odoo8_addon_profiler-8.0.1.0.0-py2.7-nspkg.pth
odoo8_addon_profiler-8.0.1.0.0.dist-info/DESCRIPTION.rst
odoo8_addon_profiler-8.0.1.0.0.dist-info/METADATA
odoo8_addon_profiler-8.0.1.0.0.dist-info/RECORD
odoo8_addon_profiler-8.0.1.0.0.dist-info/WHEEL
odoo8_addon_profiler-8.0.1.0.0.dist-info/metadata.json
odoo8_addon_profiler-8.0.1.0.0.dist-info/namespace_packages.txt
odoo8_addon_profiler-8.0.1.0.0.dist-info/top_level.txt
odoo_addons/profiler/README.rst
odoo_addons/profiler/__init__.py
odoo_addons/profiler/__openerp__.py
odoo_addons/profiler/hooks.py
odoo_addons/profiler/controllers/__init__.py
odoo_addons/profiler/controllers/main.py
odoo_addons/profiler/data/profiler_excluding.xml
odoo_addons/profiler/security/group.xml
odoo_addons/profiler/static/description/clear_stats.png
odoo_addons/profiler/static/description/dump_stats.png
odoo_addons/profiler/static/description/player.png
odoo_addons/profiler/static/description/start_profiling.png
odoo_addons/profiler/static/description/stop_profiling.png
odoo_addons/profiler/static/src/css/player.css
odoo_addons/profiler/static/src/js/player.js
odoo_addons/profiler/static/src/js/test_profiler.js
odoo_addons/profiler/static/src/less/player.less
odoo_addons/profiler/static/src/xml/player.xml
odoo_addons/profiler/tests/__init__.py
odoo_addons/profiler/tests/test_profiler.py
odoo_addons/profiler/views/assets.xml
odoo_addons/profiler/views/profiler.xml
